{
    "visual": {
        "name": "calendarvisual",
        "displayName": "calendarvisual",
        "guid": "calendarvisual514C7B9FA20F466685C31EC86F520CEE",
        "visualClassName": "Visual",
        "version": "1.0.0",
        "description": "",
        "supportUrl": "",
        "gitHubUrl": ""
    },
    "apiVersion": "2.6.0",
    "author": {
        "name": "",
        "email": ""
    },
    "assets": {
        "icon": "assets/icon.png"
    },
    "externalJS": [
        "node_modules/d3/d3.min.js"
    ],
    "style": "style/visual.less",
    "capabilities": "capabilities.json",
    "dependencies": null,
    "stringResources": []
}